{"data":{"site":{"siteMetadata":{"title":"Blog by Nahid Saikat","subtitle":"Pythonista | JavaScripter | Software Engineer | Reader"}},"allMarkdownRemark":{"edges":[{"node":{"fields":{"slug":"/blog/process-aws-dynamodb-streams-by-aws-lambda-with-terraform/","categorySlug":"/category/aws/"},"frontmatter":{"title":"Process AWS DynamoDB Streams by AWS Lambda with Terraform","date":"2020-10-06T00:12:03.284Z","category":"AWS","description":"Python 3.9 is released on 5th October, 2020 and is now available. It comes with some of the great features and lots of improvements."}}}]}},"pageContext":{"isCreatedByStatefulCreatePages":false,"tag":"AWS DynamoDB","currentPage":0,"postsLimit":6,"postsOffset":0,"prevPagePath":"/tag/aws-dynamo-db","nextPagePath":"/tag/aws-dynamo-db/page/1","hasPrevPage":false,"hasNextPage":false}}